[
    {
        "Unit" : "iommu_0",
        "PerPkg": "1",
        "MetricExpr": "100 * IOMMU.IOTLB_H_0 / (IOMMU.IOTLB_H_0 + IOMMU.IOTLB_M_0)",
        "MetricGroup": "uncore_0",
        "MetricName": "iotlb_hit_rate_0",
        "BriefDescription": "процент попаданий в IOTLB в 0 ноде = iommu.iotlb_h_0 / (iommu.iotlb_h_0 + iommu.iotlb_m_0)",
    },
    {
        "Unit" : "iommu_0",
        "PerPkg": "1",
        "MetricExpr": "100 * IOMMU.FLTLU_H_0 / (IOMMU.FLTLU_H_0 + IOMMU.FLTLU_M_0)",
        "MetricGroup": "uncore_0",
        "MetricName": "fltlu_hit_rate_0",
        "BriefDescription": "процент попаданий в IOMMU.FLTLU в 0 ноде = iommu.fltlu_h_0 / (iommu.fltlu_h_0 + iommu.fltlu_m_0)",
    },
    {
        "Unit" : "iommu_0",
        "PerPkg": "1",
        "MetricExpr": "100 * IOMMU.SLTLU_H_0 / (IOMMU.SLTLU_H_0 + IOMMU.SLTLU_M_0)",
        "MetricGroup": "uncore_0",
        "MetricName": "sltlu_hit_rate_0",
        "BriefDescription": "процент попаданий в IOMMU.SLTLU в 0 ноде = iommu.sltlu_h_0 / (iommu.sltlu_h_0 + iommu.sltlu_m_0)",
    },
    {
        "Unit" : "iommu_0",
        "PerPkg": "1",
        "MetricExpr": "100 * IOMMU.DTLB_H_0 / (IOMMU.DTLB_H_0 + IOMMU.DTLB_M_0)",
        "MetricGroup": "uncore_0",
        "MetricName": "iommu_dtlb_hit_rate_0",
        "BriefDescription": "процент попаданий в IOMMU.DTLB в 0 ноде = iommu.dtlb_h_0 / (iommu.dtlb_h_0 + iommu.dtlb_m_0)",
    },
    {
        "Unit" : "iommu_1",
        "PerPkg": "1",
        "MetricExpr": "100 * IOMMU.IOTLB_H_1 / (IOMMU.IOTLB_H_1 + IOMMU.IOTLB_M_1)",
        "MetricGroup": "uncore_1",
        "MetricName": "iotlb_hit_rate_1",
        "BriefDescription": "процент попаданий в IOTLB в 1 ноде = iommu.iotlb_h_1 / (iommu.iotlb_h_1 + iommu.iotlb_m_1)",
    },
    {
        "Unit" : "iommu_1",
        "PerPkg": "1",
        "MetricExpr": "100 * IOMMU.FLTLU_H_1 / (IOMMU.FLTLU_H_1 + IOMMU.FLTLU_M_1)",
        "MetricGroup": "uncore_1",
        "MetricName": "fltlu_hit_rate_1",
        "BriefDescription": "процент попаданий в IOMMU.FLTLU в 1 ноде = iommu.fltlu_h_1 / (iommu.fltlu_h_1 + iommu.fltlu_m_1)",
    },
    {
        "Unit" : "iommu_1",
        "PerPkg": "1",
        "MetricExpr": "100 * IOMMU.SLTLU_H_1 / (IOMMU.SLTLU_H_1 + IOMMU.SLTLU_M_1)",
        "MetricGroup": "uncore_1",
        "MetricName": "sltlu_hit_rate_1",
        "BriefDescription": "процент попаданий в IOMMU.SLTLU в 1 ноде = iommu.sltlu_h_1 / (iommu.sltlu_h_1 + iommu.sltlu_m_1)",
    },
    {
        "Unit" : "iommu_1",
        "PerPkg": "1",
        "MetricExpr": "100 * IOMMU.DTLB_H_1 / (IOMMU.DTLB_H_1 + IOMMU.DTLB_M_1)",
        "MetricGroup": "uncore_1",
        "MetricName": "iommu_dtlb_hit_rate_1",
        "BriefDescription": "процент попаданий в IOMMU.DTLB в 1 ноде = iommu.dtlb_h_1 / (iommu.dtlb_h_1 + iommu.dtlb_m_1)",
    },
    {
        "Unit" : "iommu_2",
        "PerPkg": "1",
        "MetricExpr": "100 * IOMMU.IOTLB_H_2 / (IOMMU.IOTLB_H_2 + IOMMU.IOTLB_M_2)",
        "MetricGroup": "uncore_2",
        "MetricName": "iotlb_hit_rate_2",
        "BriefDescription": "процент попаданий в IOTLB во 2 ноде = iommu.iotlb_h_2 / (iommu.iotlb_h_2 + iommu.iotlb_m_2)",
    },
    {
        "Unit" : "iommu_2",
        "PerPkg": "1",
        "MetricExpr": "100 * IOMMU.FLTLU_H_2 / (IOMMU.FLTLU_H_2 + IOMMU.FLTLU_M_2)",
        "MetricGroup": "uncore_2",
        "MetricName": "fltlu_hit_rate_2",
        "BriefDescription": "процент попаданий в IOMMU.FLTLU во 2 ноде = iommu.fltlu_h_2 / (iommu.fltlu_h_2 + iommu.fltlu_m_2)",
    },
    {
        "Unit" : "iommu_2",
        "PerPkg": "1",
        "MetricExpr": "100 * IOMMU.SLTLU_H_2 / (IOMMU.SLTLU_H_2 + IOMMU.SLTLU_M_2)",
        "MetricGroup": "uncore_2",
        "MetricName": "sltlu_hit_rate_2",
        "BriefDescription": "процент попаданий в IOMMU.SLTLU во 2 ноде = iommu.sltlu_h_2 / (iommu.sltlu_h_2 + iommu.sltlu_m_2)",
    },
    {
        "Unit" : "iommu_2",
        "PerPkg": "1",
        "MetricExpr": "100 * IOMMU.DTLB_H_2 / (IOMMU.DTLB_H_2 + IOMMU.DTLB_M_2)",
        "MetricGroup": "uncore_2",
        "MetricName": "iommu_dtlb_hit_rate_2",
        "BriefDescription": "процент попаданий в IOMMU.DTLB во 2 ноде = iommu.dtlb_h_2 / (iommu.dtlb_h_2 + iommu.dtlb_m_2)",
    },
    {
        "Unit" : "iommu_3",
        "PerPkg": "1",
        "MetricExpr": "100 * IOMMU.IOTLB_H_3 / (IOMMU.IOTLB_H_3 + IOMMU.IOTLB_M_3)",
        "MetricGroup": "uncore_3",
        "MetricName": "iotlb_hit_rate_3",
        "BriefDescription": "процент попаданий в IOTLB в 3 ноде = iommu.iotlb_h_3 / (iommu.iotlb_h_3 + iommu.iotlb_m_3)",
    },
    {
        "Unit" : "iommu_3",
        "PerPkg": "1",
        "MetricExpr": "100 * IOMMU.FLTLU_H_3 / (IOMMU.FLTLU_H_3 + IOMMU.FLTLU_M_3)",
        "MetricGroup": "uncore_3",
        "MetricName": "fltlu_hit_rate_3",
        "BriefDescription": "процент попаданий в IOMMU.FLTLU в 3 ноде = iommu.fltlu_h_3 / (iommu.fltlu_h_3 + iommu.fltlu_m_3)",
    },
    {
        "Unit" : "iommu_3",
        "PerPkg": "1",
        "MetricExpr": "100 * IOMMU.SLTLU_H_3 / (IOMMU.SLTLU_H_3 + IOMMU.SLTLU_M_3)",
        "MetricGroup": "uncore_3",
        "MetricName": "sltlu_hit_rate_3",
        "BriefDescription": "процент попаданий в IOMMU.SLTLU в 3 ноде = iommu.sltlu_h_3 / (iommu.sltlu_h_3 + iommu.sltlu_m_3)",
    },
    {
        "Unit" : "iommu_3",
        "PerPkg": "1",
        "MetricExpr": "100 * IOMMU.DTLB_H_3 / (IOMMU.DTLB_H_3 + IOMMU.DTLB_M_3)",
        "MetricGroup": "uncore_3",
        "MetricName": "iommu_dtlb_hit_rate_3",
        "BriefDescription": "процент попаданий в IOMMU.DTLB в 3 ноде = iommu.dtlb_h_3 / (iommu.dtlb_h_3 + iommu.dtlb_m_3)",
    },
    {
        "Unit" : "prepic_0",
        "PerPkg": "1",
        "MetricExpr": "100 * PREPIC.DAT_HIT_0 / (PREPIC.DAT_HIT_0 + PREPIC.DAT_MISS_0)",
        "MetricGroup": "uncore_0",
        "MetricName": "prepic_dat_hit_rate_0",
        "BriefDescription": "процент попаданий в PREPIC DAT в 0 ноде = prepic.dat_hit_0 / (prepic.dat_hit_0 + prepic.dat_miss_0)",
    },
    {
        "Unit" : "prepic_1",
        "PerPkg": "1",
        "MetricExpr": "100 * PREPIC.DAT_HIT_1 / (PREPIC.DAT_HIT_1 + PREPIC.DAT_MISS_1)",
        "MetricGroup": "uncore_1",
        "MetricName": "prepic_dat_hit_rate_1",
        "BriefDescription": "процент попаданий в PREPIC DAT в 1 ноде = prepic.dat_hit_1 / (prepic.dat_hit_1 + prepic.dat_miss_1)",
    },
    {
       "Unit" : "prepic_2",
       "PerPkg": "1",
       "MetricExpr": "100 * PREPIC.DAT_HIT_2 / (PREPIC.DAT_HIT_2 + PREPIC.DAT_MISS_2)",
       "MetricGroup": "uncore_2",
       "MetricName": "prepic_dat_hit_rate_2",
       "BriefDescription": "процент попаданий в PREPIC DAT в 2 ноде = prepic.dat_hit_2 / (prepic.dat_hit_2 + prepic.dat_miss_2)",
    },
    {
       "Unit" : "prepic_3",
       "PerPkg": "1",
       "MetricExpr": "100 * PREPIC.DAT_HIT_3 / (PREPIC.DAT_HIT_3 + PREPIC.DAT_MISS_3)",
       "MetricGroup": "uncore_3",
       "MetricName": "prepic_dat_hit_rate_3",
       "BriefDescription": "процент попаданий в PREPIC DAT в 3 ноде = prepic.dat_hit_3 / (prepic.dat_hit_3 + prepic.dat_miss_3)",
    },
]
